[
    {
        "image": "https://cdn.discordapp.com/attachments/1085883980135534653/1088943380769275914/Screenshot_2023-03-24_at_2.51.34_PM.png",
        "logo": "https://cdn.discordapp.com/attachments/1085883980135534653/1088943914557391000/logo.png",
        "title": "Zenweet",
        "text": "We know it looks like Twitter. But we love him more than Twitter.",
        "link": "https://zenweet.com"
    },
    {
        "image": "https://cdn.discordapp.com/attachments/1085883980135534653/1088990702018510889/Screenshot_2023-03-24_at_6.00.08_PM.png",
        "logo": "https://cdn.discordapp.com/avatars/1086673130577203240/416a786918c590db9ccb0d238c034d5c.webp?size=1024",
        "title": "ozturk.rip",
        "text": "My personal website where I introduce myself and which includes my projects",
        "link": "https://ozturk.rip"
    },
    {
        "image": "",
        "logo": "",
        "title": "",
        "text": "",
        "link": ""
    },
    {
        "image": "",
        "logo": "",
        "title": "",
        "text": "",
        "link": ""
    },
    {
        "image": "",
        "logo": "",
        "title": "",
        "text": "",
        "link": ""
    },
    {
        "image": "",
        "logo": "",
        "title": "Serity",
        "text": "",
        "link": ""
    }
]